{ "frames": {
   "UI_FlatAnimated 0.aseprite": {
    "frame": { "x": 1, "y": 1, "w": 32, "h": 32 },
    "rotated": false,
    "trimmed": false,
    "spriteSourceSize": { "x": 0, "y": 0, "w": 32, "h": 32 },
    "sourceSize": { "w": 32, "h": 32 },
    "duration": 100
   },
   "UI_FlatAnimated 1.aseprite": {
    "frame": { "x": 34, "y": 1, "w": 32, "h": 32 },
    "rotated": false,
    "trimmed": false,
    "spriteSourceSize": { "x": 0, "y": 0, "w": 32, "h": 32 },
    "sourceSize": { "w": 32, "h": 32 },
    "duration": 100
   },
   "UI_FlatAnimated 2.aseprite": {
    "frame": { "x": 67, "y": 1, "w": 32, "h": 32 },
    "rotated": false,
    "trimmed": false,
    "spriteSourceSize": { "x": 0, "y": 0, "w": 32, "h": 32 },
    "sourceSize": { "w": 32, "h": 32 },
    "duration": 100
   },
   "UI_FlatAnimated 3.aseprite": {
    "frame": { "x": 100, "y": 1, "w": 32, "h": 32 },
    "rotated": false,
    "trimmed": false,
    "spriteSourceSize": { "x": 0, "y": 0, "w": 32, "h": 32 },
    "sourceSize": { "w": 32, "h": 32 },
    "duration": 100
   },
   "UI_FlatAnimated 4.aseprite": {
    "frame": { "x": 133, "y": 1, "w": 32, "h": 32 },
    "rotated": false,
    "trimmed": false,
    "spriteSourceSize": { "x": 0, "y": 0, "w": 32, "h": 32 },
    "sourceSize": { "w": 32, "h": 32 },
    "duration": 100
   },
   "UI_FlatAnimated 5.aseprite": {
    "frame": { "x": 166, "y": 1, "w": 32, "h": 32 },
    "rotated": false,
    "trimmed": false,
    "spriteSourceSize": { "x": 0, "y": 0, "w": 32, "h": 32 },
    "sourceSize": { "w": 32, "h": 32 },
    "duration": 100
   },
   "UI_FlatAnimated 6.aseprite": {
    "frame": { "x": 199, "y": 1, "w": 32, "h": 32 },
    "rotated": false,
    "trimmed": false,
    "spriteSourceSize": { "x": 0, "y": 0, "w": 32, "h": 32 },
    "sourceSize": { "w": 32, "h": 32 },
    "duration": 100
   },
   "UI_FlatAnimated 7.aseprite": {
    "frame": { "x": 232, "y": 1, "w": 32, "h": 32 },
    "rotated": false,
    "trimmed": false,
    "spriteSourceSize": { "x": 0, "y": 0, "w": 32, "h": 32 },
    "sourceSize": { "w": 32, "h": 32 },
    "duration": 100
   },
   "UI_FlatAnimated 8.aseprite": {
    "frame": { "x": 265, "y": 1, "w": 32, "h": 32 },
    "rotated": false,
    "trimmed": false,
    "spriteSourceSize": { "x": 0, "y": 0, "w": 32, "h": 32 },
    "sourceSize": { "w": 32, "h": 32 },
    "duration": 100
   },
   "UI_FlatAnimated 9.aseprite": {
    "frame": { "x": 298, "y": 1, "w": 32, "h": 32 },
    "rotated": false,
    "trimmed": false,
    "spriteSourceSize": { "x": 0, "y": 0, "w": 32, "h": 32 },
    "sourceSize": { "w": 32, "h": 32 },
    "duration": 100
   },
   "UI_FlatAnimated 10.aseprite": {
    "frame": { "x": 331, "y": 1, "w": 32, "h": 32 },
    "rotated": false,
    "trimmed": false,
    "spriteSourceSize": { "x": 0, "y": 0, "w": 32, "h": 32 },
    "sourceSize": { "w": 32, "h": 32 },
    "duration": 100
   },
   "UI_FlatAnimated 11.aseprite": {
    "frame": { "x": 364, "y": 1, "w": 32, "h": 32 },
    "rotated": false,
    "trimmed": false,
    "spriteSourceSize": { "x": 0, "y": 0, "w": 32, "h": 32 },
    "sourceSize": { "w": 32, "h": 32 },
    "duration": 100
   },
   "UI_FlatAnimated 12.aseprite": {
    "frame": { "x": 397, "y": 1, "w": 32, "h": 32 },
    "rotated": false,
    "trimmed": false,
    "spriteSourceSize": { "x": 0, "y": 0, "w": 32, "h": 32 },
    "sourceSize": { "w": 32, "h": 32 },
    "duration": 100
   },
   "UI_FlatAnimated 13.aseprite": {
    "frame": { "x": 430, "y": 1, "w": 32, "h": 32 },
    "rotated": false,
    "trimmed": false,
    "spriteSourceSize": { "x": 0, "y": 0, "w": 32, "h": 32 },
    "sourceSize": { "w": 32, "h": 32 },
    "duration": 100
   },
   "UI_FlatAnimated 14.aseprite": {
    "frame": { "x": 463, "y": 1, "w": 32, "h": 32 },
    "rotated": false,
    "trimmed": false,
    "spriteSourceSize": { "x": 0, "y": 0, "w": 32, "h": 32 },
    "sourceSize": { "w": 32, "h": 32 },
    "duration": 100
   },
   "UI_FlatAnimated 15.aseprite": {
    "frame": { "x": 496, "y": 1, "w": 32, "h": 32 },
    "rotated": false,
    "trimmed": false,
    "spriteSourceSize": { "x": 0, "y": 0, "w": 32, "h": 32 },
    "sourceSize": { "w": 32, "h": 32 },
    "duration": 100
   }
 },
 "meta": {
  "app": "https://www.aseprite.org/",
  "version": "1.3.17.2-x64",
  "image": "animated_select_buttons.png",
  "format": "RGBA8888",
  "size": { "w": 529, "h": 34 },
  "scale": "1",
  "frameTags": [
   { "name": "Select01a", "from": 0, "to": 3, "direction": "forward", "color": "#000000ff" },
   { "name": "Select02a", "from": 4, "to": 7, "direction": "forward", "color": "#000000ff" },
   { "name": "Button01a", "from": 8, "to": 11, "direction": "forward", "color": "#000000ff" },
   { "name": "Button02a", "from": 12, "to": 15, "direction": "forward", "color": "#000000ff" }
  ],
  "layers": [
   { "name": "Layer 1", "opacity": 255, "blendMode": "normal" }
  ],
  "slices": [
  ]
 }
}
